odoo/addons/account_chart_update_multilang/README.rst
odoo/addons/account_chart_update_multilang/__init__.py
odoo/addons/account_chart_update_multilang/__manifest__.py
odoo/addons/account_chart_update_multilang/i18n/account_chart_update_multilang.pot
odoo/addons/account_chart_update_multilang/i18n/it.po
odoo/addons/account_chart_update_multilang/readme/CONFIGURE.md
odoo/addons/account_chart_update_multilang/readme/CONTRIBUTORS.md
odoo/addons/account_chart_update_multilang/readme/DESCRIPTION.md
odoo/addons/account_chart_update_multilang/readme/USAGE.md
odoo/addons/account_chart_update_multilang/static/description/icon.png
odoo/addons/account_chart_update_multilang/static/description/index.html
odoo/addons/account_chart_update_multilang/tests/__init__.py
odoo/addons/account_chart_update_multilang/tests/test_account_chart_update_multilang.py
odoo/addons/account_chart_update_multilang/wizards/__init__.py
odoo/addons/account_chart_update_multilang/wizards/wizard_chart_update.py
odoo/addons/account_chart_update_multilang/wizards/wizard_chart_update_views.xml
odoo_addon_account_chart_update_multilang-16.0.1.0.3.dist-info/METADATA
odoo_addon_account_chart_update_multilang-16.0.1.0.3.dist-info/WHEEL
odoo_addon_account_chart_update_multilang-16.0.1.0.3.dist-info/top_level.txt
odoo_addon_account_chart_update_multilang-16.0.1.0.3.dist-info/RECORD
